teelebot/__init__.py
teelebot/__main__.py
teelebot/bot.py
teelebot/buffer.py
teelebot/common.py
teelebot/handler.py
teelebot/logger.py
teelebot/main.py
teelebot/metadata.py
teelebot/polling.py
teelebot/request.py
teelebot/schedule.py
teelebot/version.py
teelebot/webhook.py
teelebot-2.6.0.dist-info/licenses/LICENSE
teelebot-2.6.0.dist-info/METADATA
teelebot-2.6.0.dist-info/WHEEL
teelebot-2.6.0.dist-info/entry_points.txt
teelebot-2.6.0.dist-info/top_level.txt
teelebot-2.6.0.dist-info/zip-safe
teelebot-2.6.0.dist-info/RECORD
