Metadata-Version: 2.4
Name: teelebot
Version: 2.6.0
Summary: teelebot is a Python-based Telegram Bot framework with a plugin system that supports hot reload and hot loading.
Home-page: https://ojoll.com
Author: Pluto
Author-email: hi@ojoll.com
License: GPLv3
Keywords: teelebot telegram bot telegram bot api telegram
Classifier: Programming Language :: Python :: 3
Classifier: Operating System :: OS Independent
Classifier: License :: OSI Approved :: GNU General Public License v3 (GPLv3)
Requires-Python: >=3.6
License-File: LICENSE
Requires-Dist: requests[socks]
Dynamic: author
Dynamic: author-email
Dynamic: classifier
Dynamic: description
Dynamic: description-content-type
Dynamic: home-page
Dynamic: keywords
Dynamic: license
Dynamic: license-file
Dynamic: requires-dist
Dynamic: requires-python
Dynamic: summary
